[{"anilist_id":97881,"bgm_id":183891},{"anilist_id":20628,"bgm_id":null},{"anilist_id":20574,"bgm_id":91205},{"anilist_id":21746,"bgm_id":175399},{"anilist_id":21127,"bgm_id":129807},{"anilist_id":97604,"bgm_id":191323},{"anilist_id":98217,"bgm_id":207932},{"anilist_id":87495,"bgm_id":190441},{"anilist_id":97768,"bgm_id":195843},{"anilist_id":97907,"bgm_id":200589},{"anilist_id":21717,"bgm_id":175601},{"anilist_id":21879,"bgm_id":185789},{"anilist_id":87504,"bgm_id":190254},{"anilist_id":97767,"bgm_id":195845},{"anilist_id":21827,"bgm_id":183878},{"anilist_id":21451,"bgm_id":150246},{"anilist_id":21748,"bgm_id":175398},{"anilist_id":97832,"bgm_id":198098},{"anilist_id":21712,"bgm_id":175404},{"anilist_id":98034,"bgm_id":204027}]